HISTORY.rst
MANIFEST.in
README.rst
setup.cfg
setup.py
buildout/__init__.py
buildout.variables.egg-info/PKG-INFO
buildout.variables.egg-info/SOURCES.txt
buildout.variables.egg-info/dependency_links.txt
buildout.variables.egg-info/entry_points.txt
buildout.variables.egg-info/namespace_packages.txt
buildout.variables.egg-info/requires.txt
buildout.variables.egg-info/top_level.txt
buildout/variables/__init__.py
buildout/variables/test_variables.py