Metadata-Version: 1.0
Name: buildout.variables
Version: 0.3
Summary: Provides dynamic variables in buildouts
Home-page: http://github.com/fschulze/buildout.variables
Author: Florian Schulze
Author-email: florian.schulze@gmx.net
License: GPL
Platform: UNKNOWN
